codeforces_scraper/__init__.py
codeforces_scraper/languages.py
codeforces_scraper/models.py
codeforces_scraper/scraper.py
codeforces_scraper/utils.py
codeforces_scraper/assets/__init__.py
codeforces_scraper/assets/all_language_compilers.json
codeforces_scraper-0.4.0.dist-info/LICENSE
codeforces_scraper-0.4.0.dist-info/METADATA
codeforces_scraper-0.4.0.dist-info/WHEEL
codeforces_scraper-0.4.0.dist-info/top_level.txt
codeforces_scraper-0.4.0.dist-info/zip-safe
codeforces_scraper-0.4.0.dist-info/RECORD
